DESC.md
LICENSE
MANIFEST.in
README.md
setup.cfg
setup.py
pi_MCP4725/MCP4725.py
pi_MCP4725/__init__.py
pi_MCP4725.egg-info/PKG-INFO
pi_MCP4725.egg-info/SOURCES.txt
pi_MCP4725.egg-info/dependency_links.txt
pi_MCP4725.egg-info/requires.txt
pi_MCP4725.egg-info/top_level.txt