Metadata-Version: 2.1
Name: pi-MCP4725
Version: 0.1.2
Summary: Python module to use the MCP4725 DAC with the Raspberry Pi
Home-page: https://github.com/sergiocaponi/pi_MCP4725
Download-URL: https://github.com/sergiocaponi/pi_MCP4725/archive/refs/tags/v0.1.2.tar.gz
Author: Sergio Caponi
Author-email: contactme@sergiocaponi.com
License: MIT
Keywords: Raspberry Pi,DAC,MCP4725
Classifier: Development Status :: 3 - Alpha
Classifier: Intended Audience :: Developers
Classifier: Operating System :: POSIX :: Linux
Classifier: Topic :: Software Development :: Build Tools
Classifier: Topic :: System :: Hardware
Classifier: License :: OSI Approved :: MIT License
Classifier: Programming Language :: Python :: 3
License-File: LICENSE
